MANIFEST.in
README.txt
TODO.txt
run_enrich
setup.py
enrich/__init__.py
enrich/all_exceptions.py
enrich/central_hub.py
enrich/document_handler.py
enrich/export.py
enrich/input_handler.py
enrich/input_ob.py
enrich/source_ob.py
enrich/stat_compare.py
enrich/update_enrichment.py
enrich/docs/all_nodes.test.txt
enrich/docs/clusters.test.txt
enrich/docs/gene_ontology.group_info.txt
enrich/docs/gene_ontology.groupings.txt
west_enrich.egg-info/PKG-INFO
west_enrich.egg-info/SOURCES.txt
west_enrich.egg-info/dependency_links.txt
west_enrich.egg-info/entry_points.txt
west_enrich.egg-info/top_level.txt